freegpts/__init__.py
freegpts/gpt4.py
freegpts/gpt4o.py
freegpts/gpt4omini.py
freegpts-1.1.0.dist-info/METADATA
freegpts-1.1.0.dist-info/WHEEL
freegpts-1.1.0.dist-info/top_level.txt
freegpts-1.1.0.dist-info/RECORD
